krakenPythonMarcosRodrigo/__init__.py
krakenpythonmarcosrodrigo-0.1.2.dist-info/METADATA
krakenpythonmarcosrodrigo-0.1.2.dist-info/WHEEL
krakenpythonmarcosrodrigo-0.1.2.dist-info/RECORD
