Metadata-Version: 2.1
Name: KrakenPythonMarcosRodrigo
Version: 0.1.2
Summary: A streamlit tool for rendering kraken data
Author: Your Name
Author-email: you@example.com
Requires-Python: >=3.11,<4.0
Classifier: Programming Language :: Python :: 3
Classifier: Programming Language :: Python :: 3.11
Classifier: Programming Language :: Python :: 3.12
Requires-Dist: coverage (==5.5)
Requires-Dist: krakenex (==2.1.0)
Requires-Dist: numpy (==1.26.2)
Requires-Dist: pandas (==2.1.4)
Requires-Dist: plotly (==5.18.0)
Requires-Dist: protobuf (==3.20.0)
Requires-Dist: streamlit (==1.29.0)
Requires-Dist: streamlit-option-menu (==0.3.6)
